know_your_ip/__init__.py
know_your_ip/config.py
know_your_ip/know_your_ip.py
know_your_ip/ping.py
know_your_ip/traceroute.py
know_your_ip-0.2.1.dist-info/licenses/LICENSE
know_your_ip-0.2.1.dist-info/METADATA
know_your_ip-0.2.1.dist-info/WHEEL
know_your_ip-0.2.1.dist-info/entry_points.txt
know_your_ip-0.2.1.dist-info/top_level.txt
know_your_ip-0.2.1.dist-info/RECORD
