Metadata-Version: 2.4
Name: know_your_ip
Version: 0.2.1
Summary: Get data on IP addresses
Author-email: Suriyan Laohaprapanon <suriyant@gmail.com>, Gaurav Sood <gsood07@gmail.com>
License-Expression: MIT
Project-URL: Homepage, https://github.com/themains/know-your-ip
Project-URL: Repository, https://github.com/themains/know-your-ip
Project-URL: Documentation, https://themains.github.io/know-your-ip/
Project-URL: Bug Tracker, https://github.com/themains/know-your-ip/issues
Keywords: ip,geoip,ipvoid,abuseip,shodan,virustotal,blacklisted,geolocation,cybersecurity
Classifier: Development Status :: 4 - Beta
Classifier: Intended Audience :: Developers
Classifier: Intended Audience :: System Administrators
Classifier: Programming Language :: Python :: 3
Classifier: Programming Language :: Python :: 3.11
Classifier: Programming Language :: Python :: 3.12
Classifier: Programming Language :: Python :: 3.13
Classifier: Topic :: Internet
Classifier: Topic :: Security
Classifier: Topic :: Scientific/Engineering :: Information Analysis
Classifier: Topic :: Software Development :: Libraries :: Python Modules
Classifier: Topic :: System :: Networking
Classifier: Topic :: Utilities
Requires-Python: >=3.11
License-File: LICENSE
Requires-Dist: geoip2
Requires-Dist: tzwhere
Requires-Dist: BeautifulSoup4
Requires-Dist: lxml
Requires-Dist: shodan
Requires-Dist: requests
Requires-Dist: pydantic>=2.0
Provides-Extra: dev
Requires-Dist: ruff; extra == "dev"
Requires-Dist: pytest; extra == "dev"
Requires-Dist: pytest-cov; extra == "dev"
Requires-Dist: pre-commit; extra == "dev"
Requires-Dist: build; extra == "dev"
Requires-Dist: twine; extra == "dev"
Provides-Extra: test
Requires-Dist: pytest; extra == "test"
Requires-Dist: pytest-cov; extra == "test"
Requires-Dist: pytest-mock; extra == "test"
Provides-Extra: docs
Requires-Dist: sphinx>=7.0; extra == "docs"
Requires-Dist: furo; extra == "docs"
Requires-Dist: sphinx-copybutton; extra == "docs"
Requires-Dist: myst-parser; extra == "docs"
Dynamic: license-file
